boiler/__init__.py
boiler/bootstrap.py
boiler/config.py
boiler/errors.py
boiler/events.py
boiler/exceptions.py
boiler/version.py
boiler/_requirements/all.txt
boiler/_requirements/api.txt
boiler/_requirements/flask.txt
boiler/_requirements/localization.txt
boiler/_requirements/mail.txt
boiler/_requirements/orm.txt
boiler/_requirements/testing.txt
boiler/abstract/__init__.py
boiler/abstract/abstract_service.py
boiler/boiler_template/cli
boiler/boiler_template/dist.env
boiler/boiler_template/dist.gitignore
boiler/boiler_template/nose.ini
boiler/boiler_template/uwsgi.ini
boiler/boiler_template/wsgi.py
boiler/boiler_template/backend/app.py
boiler/boiler_template/backend/config.py
boiler/boiler_template/backend/urls.py
boiler/boiler_template/backend/views.py
boiler/boiler_template/backend/templates/layout.j2
boiler/boiler_template/backend/templates/index/home.j2
boiler/boiler_template/var/.gitkeep
boiler/boiler_template/var/data/.gitkeep
boiler/boiler_template/var/logs/.gitkeep
boiler/cli/__init__.py
boiler/cli/boiler.py
boiler/cli/cli.py
boiler/cli/colors.py
boiler/cli/db.py
boiler/collections/__init__.py
boiler/collections/api_collection.py
boiler/collections/paginated_collection.py
boiler/collections/pagination.py
boiler/feature/__init__.py
boiler/feature/localization.py
boiler/feature/logging.py
boiler/feature/mail.py
boiler/feature/orm.py
boiler/feature/routing.py
boiler/jinja/__init__.py
boiler/jinja/functions.py
boiler/log/__init__.py
boiler/log/datadog.py
boiler/log/file.py
boiler/log/mail.py
boiler/migrations/__init__.py
boiler/migrations/config.py
boiler/migrations/templates/__init__.py
boiler/migrations/templates/project/__init__.py
boiler/migrations/templates/project/alembic.ini.mako
boiler/migrations/templates/project/env.py
boiler/migrations/templates/project/script.py.mako
boiler/routes/__init__.py
boiler/routes/lazy_views.py
boiler/routes/regex.py
boiler/routes/route.py
boiler/templates/kernel_layout.j2
boiler/templates/errors/400.j2
shiftboiler-0.11.2.dist-info/LICENSE.txt
shiftboiler-0.11.2.dist-info/METADATA
shiftboiler-0.11.2.dist-info/WHEEL
shiftboiler-0.11.2.dist-info/entry_points.txt
shiftboiler-0.11.2.dist-info/top_level.txt
shiftboiler-0.11.2.dist-info/RECORD
