Metadata-Version: 2.1
Name: shiftboiler
Version: 0.11.2
Summary: Boilerplate setup for webapps, apis and cli applications with flask
Home-page: https://github.com/projectshift/shift-boiler
Download-URL: https://github.com/projectshift/shift-boiler/archive/v0.11.2.tar.gz
Author: Dmitry Belyakov
Author-email: dmitrybelyakov@gmail.com
License: MIT License
Keywords: python3,flask,click,orm,sqlalchemy,webapp,api,babel
Classifier: Development Status :: 4 - Beta
Classifier: License :: OSI Approved :: MIT License
Classifier: Intended Audience :: Developers
Classifier: Intended Audience :: Information Technology
Classifier: Programming Language :: Python :: 3
Classifier: Environment :: Console
Classifier: Environment :: Web Environment
Classifier: Framework :: Flask
Classifier: Framework :: IPython
Classifier: Topic :: Internet :: WWW/HTTP :: Site Management
Classifier: Topic :: Software Development :: Libraries :: Application Frameworks
Classifier: Topic :: Utilities
License-File: LICENSE.txt
Requires-Dist: click (<9.0.0,>=8.0.0)
Requires-Dist: shiftschema (<0.4.0,>=0.3.0)
